vdt.versionplugin.wheel-0.0.8-py3.10-nspkg.pth
vdt/versionplugin/wheel/__init__.py
vdt/versionplugin/wheel/package.py
vdt/versionplugin/wheel/shared.py
vdt/versionplugin/wheel/utils.py
vdt/versionplugin/wheel/version.py
vdt.versionplugin.wheel-0.0.8.dist-info/LICENSE
vdt.versionplugin.wheel-0.0.8.dist-info/METADATA
vdt.versionplugin.wheel-0.0.8.dist-info/WHEEL
vdt.versionplugin.wheel-0.0.8.dist-info/namespace_packages.txt
vdt.versionplugin.wheel-0.0.8.dist-info/top_level.txt
vdt.versionplugin.wheel-0.0.8.dist-info/zip-safe
vdt.versionplugin.wheel-0.0.8.dist-info/RECORD
